nanogui/__init__.py
nanogui/__init__.pyi
nanogui/glfw.pyi
nanogui/icons.pyi
nanogui/include/glad/glad/glad.h
nanogui/include/glad/KHR/khrplatform.h
nanogui/include/GLFW/glfw3.h
nanogui/include/GLFW/glfw3native.h
nanogui/include/nanogui/button.h
nanogui/include/nanogui/canvas.h
nanogui/include/nanogui/checkbox.h
nanogui/include/nanogui/chroma.h
nanogui/include/nanogui/colorpass.h
nanogui/include/nanogui/colorpicker.h
nanogui/include/nanogui/colorwheel.h
nanogui/include/nanogui/combobox.h
nanogui/include/nanogui/common.h
nanogui/include/nanogui/formhelper.h
nanogui/include/nanogui/graph.h
nanogui/include/nanogui/icons.h
nanogui/include/nanogui/imagepanel.h
nanogui/include/nanogui/imageview.h
nanogui/include/nanogui/label.h
nanogui/include/nanogui/layout.h
nanogui/include/nanogui/messagedialog.h
nanogui/include/nanogui/metal.h
nanogui/include/nanogui/nanogui.h
nanogui/include/nanogui/object.h
nanogui/include/nanogui/opengl.h
nanogui/include/nanogui/popup.h
nanogui/include/nanogui/popupbutton.h
nanogui/include/nanogui/progressbar.h
nanogui/include/nanogui/python.h
nanogui/include/nanogui/quad.h
nanogui/include/nanogui/renderpass.h
nanogui/include/nanogui/screen.h
nanogui/include/nanogui/shader.h
nanogui/include/nanogui/slider.h
nanogui/include/nanogui/tabwidget.h
nanogui/include/nanogui/textarea.h
nanogui/include/nanogui/textbox.h
nanogui/include/nanogui/texture.h
nanogui/include/nanogui/theme.h
nanogui/include/nanogui/toolbutton.h
nanogui/include/nanogui/traits.h
nanogui/include/nanogui/vector.h
nanogui/include/nanogui/vscrollpanel.h
nanogui/include/nanogui/widget.h
nanogui/include/nanogui/window.h
nanogui/include/nanovg/fontstash.h
nanogui/include/nanovg/nanovg.h
nanogui/include/nanovg/nanovg_gl.h
nanogui/include/nanovg/nanovg_gl_utils.h
nanogui/include/nanovg/stb_image.h
nanogui/include/nanovg/stb_truetype.h
nanogui/ituth273.pyi
nanogui/nanogui.dll
nanogui/nanogui.lib
nanogui/nanogui_ext.cp39-win_amd64.pyd
nanogui/nanovg.pyi
nanogui/py.typed
nanogui-0.3.0.dist-info/METADATA
nanogui-0.3.0.dist-info/WHEEL
nanogui-0.3.0.dist-info/licenses/LICENSE.txt
nanogui-0.3.0.dist-info/RECORD
