Metadata-Version: 2.1
Name: nanogui
Version: 0.3.0
Summary: A minimalistic GUI library for OpenGL, GLES 2, and Metal
Author-Email: Wenzel Jakob <wenzel.jakob@epfl.ch>
License: BSD
Classifier: Development Status :: 4 - Beta
Classifier: Intended Audience :: Developers
Classifier: License :: OSI Approved :: BSD License
Classifier: Programming Language :: C++
Classifier: Programming Language :: Python :: 3
Classifier: Programming Language :: Python :: 3.8
Classifier: Programming Language :: Python :: 3.9
Classifier: Programming Language :: Python :: 3.10
Classifier: Programming Language :: Python :: 3.11
Classifier: Programming Language :: Python :: 3.12
Classifier: Topic :: Software Development :: Libraries :: Python Modules
Classifier: Topic :: Software Development :: User Interfaces
Project-URL: Homepage, https://github.com/mitsuba-renderer/nanogui
Project-URL: Repository, https://github.com/mitsuba-renderer/nanogui
Project-URL: Issues, https://github.com/mitsuba-renderer/nanogui/issues
Requires-Python: >=3.8
